crypto_allauth/__init__.py
crypto_allauth/apps.py
crypto_allauth/hashing.py
crypto_allauth/models.py
crypto_allauth/providers/__init__.py
crypto_allauth/providers/trezor/__init__.py
crypto_allauth/providers/trezor/provider.py
crypto_allauth/providers/trezor/urls.py
crypto_allauth/providers/trezor/views.py
crypto_allauth/providers/trezor/static/trezor/img/trezor_button.png
crypto_allauth/providers/trezor/static/trezor/js/connect.js
crypto_allauth/providers/trezor/templates/trezor/trezor_connect.html
crypto_allauth/tests/__init__.py
crypto_allauth/tests/test_trezor.py
crypto_allauth-0.0.5.dist-info/DESCRIPTION.rst
crypto_allauth-0.0.5.dist-info/METADATA
crypto_allauth-0.0.5.dist-info/RECORD
crypto_allauth-0.0.5.dist-info/WHEEL
crypto_allauth-0.0.5.dist-info/metadata.json
crypto_allauth-0.0.5.dist-info/top_level.txt
