Metadata-Version: 2.0
Name: crypto-allauth
Version: 0.0.5
Summary: Plugin for django-allauth that allows authentication using cryptographic tools like Trezor.
Home-page: https://github.com/Solution4Future/crypto-allauth
Author: Dominik Kozaczko
Author-email: dominik.kozaczko@solution4future.com
License: MIT
Keywords: django auth account trezor registration
Platform: UNKNOWN
Classifier: Intended Audience :: Developers
Classifier: Topic :: Software Development :: Libraries :: Python Modules
Classifier: Environment :: Web Environment
Classifier: Topic :: Internet
Classifier: License :: OSI Approved :: MIT License
Classifier: Operating System :: OS Independent
Classifier: Programming Language :: Python
Classifier: Programming Language :: Python :: 2.7
Classifier: Programming Language :: Python :: 3.2
Classifier: Programming Language :: Python :: 3.3
Classifier: Programming Language :: Python :: 3.4
Classifier: Programming Language :: Python :: 3.5
Classifier: Framework :: Django
Requires-Dist: bitcoin (>=1.1.42)
Requires-Dist: django-allauth (>=0.27.0)
